hpe3parencryptor/__init__.py
hpe3parencryptor/encryption_utility.py
py_3parencryptor-1.0.9.dist-info/LICENSE
py_3parencryptor-1.0.9.dist-info/METADATA
py_3parencryptor-1.0.9.dist-info/WHEEL
py_3parencryptor-1.0.9.dist-info/entry_points.txt
py_3parencryptor-1.0.9.dist-info/top_level.txt
py_3parencryptor-1.0.9.dist-info/RECORD
