Metadata-Version: 2.1
Name: py-3parencryptor
Version: 1.0.9
Summary: HPE 3PAR Encryption Utility
Home-page: UNKNOWN
Author: Anand Totala
Author-email: anand-totala.totala@hpe.com
Maintainer: Anand Totala
License: Apache License, Version 2.0
Keywords: hpe,3par,encryptor
Platform: UNKNOWN
Classifier: Development Status :: 5 - Production/Stable
Classifier: Intended Audience :: Developers
Classifier: License :: OSI Approved :: Apache Software License
Classifier: Programming Language :: Python
Classifier: Programming Language :: Python :: 3.6
Provides: hpe3parencryptor
Requires-Dist: python-etcd
Requires-Dist: configparser
Requires-Dist: pycrypto
